{"puzzleId":1664426901193,"puzzle":[{"adult":false,"backdrop_path":"/tuDhEdza074bA497bO9WFEPs6O6.jpg","genre_ids":[12,10751,14],"id":411,"original_language":"en","original_title":"The Chronicles of Narnia: The Lion, the Witch and the Wardrobe","overview":"Siblings Lucy, Edmund, Susan and Peter step through a magical wardrobe and find the land of Narnia. There, they discover a charming, once peaceful kingdom that has been plunged into eternal winter by the evil White Witch, Jadis. Aided by the wise and magnificent lion, Aslan, the children lead Narnia into a spectacular, climactic battle to be free of the Witch's glacial powers forever.","popularity":125.626,"poster_path":"/kzJip9vndXYSKQHCgekrgqbnUrA.jpg","release_date":"2005-12-09","title":"The Chronicles of Narnia: The Lion, the Witch and the Wardrobe","video":false,"vote_average":7.1,"vote_count":8832,"cast":[{"adult":false,"gender":2,"id":5527,"known_for_department":"Acting","name":"Skandar Keynes","original_name":"Skandar Keynes","popularity":13.13,"profile_path":"/pIdgY16c6AzmCD31pXlCR9SjLlM.jpg","cast_id":4,"character":"Edmund Pevensie","credit_id":"52fe4240c3a36847f800fccd","order":0},{"adult":false,"gender":1,"id":5526,"known_for_department":"Acting","name":"Georgie Henley","original_name":"Georgie Henley","popularity":14.689,"profile_path":"/6qUwxWeFkgMAwCxkYGn7ISxWAZI.jpg","cast_id":3,"character":"Lucy Pevensie","credit_id":"52fe4240c3a36847f800fcc9","order":1},{"adult":false,"gender":2,"id":5528,"known_for_department":"Acting","name":"William Moseley","original_name":"William Moseley","popularity":18.668,"profile_path":"/wPahfIdOR6ohIgmgVrCb3RPApAU.jpg","cast_id":5,"character":"Peter Pevensie","credit_id":"52fe4240c3a36847f800fcd1","order":2},{"adult":false,"gender":1,"id":5529,"known_for_department":"Acting","name":"Anna Popplewell","original_name":"Anna Popplewell","popularity":21.002,"profile_path":"/fs5uYzzseA94fKC9sr0iWuCULup.jpg","cast_id":6,"character":"Susan Pevensie","credit_id":"52fe4240c3a36847f800fcd5","order":3},{"adult":false,"gender":1,"id":3063,"known_for_department":"Acting","name":"Tilda Swinton","original_name":"Tilda Swinton","popularity":61.909,"profile_path":"/gWbX3a7V2MgRMRzekfITNcb27xV.jpg","cast_id":7,"character":"White Witch","credit_id":"52fe4240c3a36847f800fcd9","order":4}],"directors":[{"adult":false,"gender":2,"id":5524,"known_for_department":"Production","name":"Andrew Adamson","original_name":"Andrew Adamson","popularity":7.785,"profile_path":"/qqIAVKAe5LHRbPyZUlptsqlo4Kb.jpg","credit_id":"52fe4240c3a36847f800fcbf","department":"Directing","job":"Director"}],"keyPerson":{"adult":false,"gender":2,"id":5527,"known_for_department":"Acting","name":"Skandar Keynes","original_name":"Skandar Keynes","popularity":13.13,"profile_path":"/pIdgY16c6AzmCD31pXlCR9SjLlM.jpg","cast_id":4,"character":"Edmund Pevensie","credit_id":"52fe4240c3a36847f800fccd","order":0}},{"adult":false,"backdrop_path":"/9pBv1BOSloAUgAkF0meJWdnbV4Q.jpg","genre_ids":[12,10751,14],"id":2454,"original_language":"en","original_title":"The Chronicles of Narnia: Prince Caspian","overview":"One year after their incredible adventures in the Lion, the Witch and the Wardrobe, Peter, Edmund, Lucy and Susan Pevensie return to Narnia to aid a young prince whose life has been threatened by the evil King Miraz. Now, with the help of a colorful cast of new characters, including Trufflehunter the badger and Nikabrik the dwarf, the Pevensie clan embarks on an incredible quest to ensure that Narnia is returned to its rightful heir.","popularity":69.254,"poster_path":"/qxz3WIyjZiSKUhaTIEJ3c1GcC9z.jpg","release_date":"2008-05-16","title":"The Chronicles of Narnia: Prince Caspian","video":false,"vote_average":6.6,"vote_count":5468,"cast":[{"adult":false,"gender":2,"id":25130,"known_for_department":"Acting","name":"Ben Barnes","original_name":"Ben Barnes","popularity":26.597,"profile_path":"/yzw4fvNWQ57ThzCb8ZqxT71mj2E.jpg","cast_id":1,"character":"Prince Caspian","credit_id":"52fe4358c3a36847f804d6ad","order":4},{"adult":false,"gender":2,"id":2166,"known_for_department":"Acting","name":"Sergio Castellitto","original_name":"Sergio Castellitto","popularity":5.763,"profile_path":"/uq5xz7kinzgdclGOcechgfPBgYC.jpg","cast_id":5,"character":"King Miraz","credit_id":"52fe4358c3a36847f804d6bd","order":5},{"adult":false,"gender":2,"id":22970,"known_for_department":"Acting","name":"Peter Dinklage","original_name":"Peter Dinklage","popularity":23.94,"profile_path":"/lRsRgnksAhBRXwAB68MFjmTtLrk.jpg","cast_id":7,"character":"Trumpkin","credit_id":"52fe4358c3a36847f804d6c5","order":6},{"adult":false,"gender":2,"id":11184,"known_for_department":"Acting","name":"Warwick Davis","original_name":"Warwick Davis","popularity":9.941,"profile_path":"/nGorSpUIQWAEErxq8KdDcIF6Q00.jpg","cast_id":8,"character":"Nikabrik","credit_id":"52fe4359c3a36847f804d6c9","order":7},{"adult":false,"gender":2,"id":25133,"known_for_department":"Acting","name":"Vincent Grass","original_name":"Vincent Grass","popularity":3.883,"profile_path":"/1F8RuqxvdKCmw5lMDG4rjyTzB6S.jpg","cast_id":9,"character":"Doktor Cornelius","credit_id":"52fe4359c3a36847f804d6cd","order":8}],"directors":[{"adult":false,"gender":2,"id":5524,"known_for_department":"Production","name":"Andrew Adamson","original_name":"Andrew Adamson","popularity":7.283,"profile_path":"/qqIAVKAe5LHRbPyZUlptsqlo4Kb.jpg","credit_id":"52fe4359c3a36847f804d6f3","department":"Directing","job":"Director"}],"keyPerson":{"adult":false,"gender":2,"id":25130,"known_for_department":"Acting","name":"Ben Barnes","original_name":"Ben Barnes","popularity":26.597,"profile_path":"/yzw4fvNWQ57ThzCb8ZqxT71mj2E.jpg","cast_id":1,"character":"Prince Caspian","credit_id":"52fe4358c3a36847f804d6ad","order":4}},{"adult":false,"backdrop_path":"/b0GGZbLB7P9r4klx1wUcz77WzE6.jpg","genre_ids":[18,53],"id":83686,"original_language":"en","original_title":"The Words","overview":"The Words follows young writer Rory Jansen who finally achieves long sought after literary success after publishing the next great American novel. There's only one catch - he didn't write it. As the past comes back to haunt him and his literary star continues to rise, Jansen is forced to confront the steep price that must be paid for stealing another man's work, and for placing ambition and success above life's most fundamental three words.","popularity":10.291,"poster_path":"/aJtPLZS7tlpiQl6pEr8H42K565x.jpg","release_date":"2012-09-07","title":"The Words","video":false,"vote_average":6.6,"vote_count":982,"cast":[{"adult":false,"gender":2,"id":51329,"known_for_department":"Acting","name":"Bradley Cooper","original_name":"Bradley Cooper","popularity":44.639,"profile_path":"/pLD2XvxqHueLWOuqXoFngJU3A5H.jpg","cast_id":4,"character":"Rory Jansen","credit_id":"52fe48b49251416c91095939","order":0},{"adult":false,"gender":1,"id":8691,"known_for_department":"Acting","name":"Zoe Saldaña","original_name":"Zoe Saldaña","popularity":50.759,"profile_path":"/iOVbUH20il632nj2v01NCtYYeSg.jpg","cast_id":5,"character":"Dora Jansen","credit_id":"52fe48b49251416c9109593d","order":1},{"adult":false,"gender":2,"id":16940,"known_for_department":"Acting","name":"Jeremy Irons","original_name":"Jeremy Irons","popularity":20.807,"profile_path":"/w8Ct1q02Ht3sWdOSqfp3B85TzT.jpg","cast_id":6,"character":"The Old Man","credit_id":"52fe48b49251416c91095941","order":2},{"adult":false,"gender":2,"id":6065,"known_for_department":"Acting","name":"Dennis Quaid","original_name":"Dennis Quaid","popularity":24.232,"profile_path":"/9z8nfkqRgEBjsb3sXQ0jMopJJOE.jpg","cast_id":7,"character":"Clay Hammond","credit_id":"52fe48b49251416c91095945","order":3},{"adult":false,"gender":1,"id":59315,"known_for_department":"Acting","name":"Olivia Wilde","original_name":"Olivia Wilde","popularity":36.162,"profile_path":"/3C7ogDK7ZrpQezMxG8ILO2ILY9a.jpg","cast_id":3,"character":"Danielle","credit_id":"52fe48b49251416c91095935","order":4}],"directors":[{"adult":false,"gender":2,"id":51996,"known_for_department":"Acting","name":"Brian Klugman","original_name":"Brian Klugman","popularity":3.887,"profile_path":"/v716uSwY5xiz8reoIuMG7ikWLS5.jpg","credit_id":"52fe48b49251416c9109592b","department":"Directing","job":"Director"},{"adult":false,"gender":0,"id":929917,"known_for_department":"Writing","name":"Lee Sternthal","original_name":"Lee Sternthal","popularity":1.7,"profile_path":null,"credit_id":"52fe48b49251416c91095931","department":"Directing","job":"Director"}],"keyPerson":{"adult":false,"gender":2,"id":51329,"known_for_department":"Acting","name":"Bradley Cooper","original_name":"Bradley Cooper","popularity":44.639,"profile_path":"/pLD2XvxqHueLWOuqXoFngJU3A5H.jpg","cast_id":4,"character":"Rory Jansen","credit_id":"52fe48b49251416c91095939","order":0}},{"adult":false,"backdrop_path":"/2UFxrUHVuSK3Tth7DvQQlF4mGTd.jpg","genre_ids":[28,878,12],"id":118340,"original_language":"en","original_title":"Guardians of the Galaxy","overview":"Light years from Earth, 26 years after being abducted, Peter Quill finds himself the prime target of a manhunt after discovering an orb wanted by Ronan the Accuser.","popularity":48.816,"poster_path":"/r7vmZjiyZw9rpJMQJdXpjgiCOk9.jpg","release_date":"2014-08-01","title":"Guardians of the Galaxy","video":false,"vote_average":7.9,"vote_count":24933,"cast":[{"adult":false,"gender":2,"id":73457,"known_for_department":"Acting","name":"Chris Pratt","original_name":"Chris Pratt","popularity":84.847,"profile_path":"/83o3koL82jt30EJ0rz4Bnzrt2dd.jpg","cast_id":361,"character":"Peter Quill / Star-Lord","credit_id":"5e85b35d691cd50014590d26","order":0},{"adult":false,"gender":2,"id":543530,"known_for_department":"Acting","name":"Dave Bautista","original_name":"Dave Bautista","popularity":29.759,"profile_path":"/26YLbFdg2M8dTOim3jWJCLfryO1.jpg","cast_id":2,"character":"Drax the Destroyer","credit_id":"52fe4bd5c3a36847f8215d05","order":2},{"adult":false,"gender":2,"id":12835,"known_for_department":"Acting","name":"Vin Diesel","original_name":"Vin Diesel","popularity":92.314,"profile_path":"/7rwSXluNWZAluYMOEWBxkPmckES.jpg","cast_id":21,"character":"Groot (voice)","credit_id":"52fe4bd5c3a36847f8215d5b","order":3},{"adult":false,"gender":2,"id":72095,"known_for_department":"Acting","name":"Lee Pace","original_name":"Lee Pace","popularity":35.901,"profile_path":"/tC4oFRqPmN0DSXGbHjqEzmfrclq.jpg","cast_id":14,"character":"Ronan the Accuser","credit_id":"52fe4bd5c3a36847f8215d3d","order":5},{"adult":false,"gender":2,"id":12132,"known_for_department":"Acting","name":"Michael Rooker","original_name":"Michael Rooker","popularity":26.011,"profile_path":"/dq3xFKDWJsQjPffm1bmB3TbMilq.jpg","cast_id":11,"character":"Yondu Udonta","credit_id":"52fe4bd5c3a36847f8215d31","order":6}],"directors":[{"adult":false,"gender":2,"id":15218,"known_for_department":"Writing","name":"James Gunn","original_name":"James Gunn","popularity":14.876,"profile_path":"/2kFzvqCGeYBrgbuuvvyGE75d9gM.jpg","credit_id":"5e85b3bd3344c6001340c95b","department":"Directing","job":"Director"}],"keyPerson":{"adult":false,"gender":2,"id":72095,"known_for_department":"Acting","name":"Lee Pace","original_name":"Lee Pace","popularity":35.901,"profile_path":"/tC4oFRqPmN0DSXGbHjqEzmfrclq.jpg","cast_id":14,"character":"Ronan the Accuser","credit_id":"52fe4bd5c3a36847f8215d3d","order":5}},{"adult":false,"backdrop_path":"/zn13a7U9eMTJq8sHthe3bCgsVm4.jpg","genre_ids":[28,12,14],"id":122917,"original_language":"en","original_title":"The Hobbit: The Battle of the Five Armies","overview":"Immediately after the events of The Desolation of Smaug, Bilbo and the dwarves try to defend Erebor's mountain of treasure from others who claim it: the men of the ruined Laketown and the elves of Mirkwood. Meanwhile an army of Orcs led by Azog the Defiler is marching on Erebor, fueled by the rise of the dark lord Sauron. Dwarves, elves and men must unite, and the hope for Middle-Earth falls into Bilbo's hands.","popularity":181.141,"poster_path":"/xT98tLqatZPQApyRmlPL12LtiWp.jpg","release_date":"2014-12-17","title":"The Hobbit: The Battle of the Five Armies","video":false,"vote_average":7.3,"vote_count":12305,"cast":[{"adult":false,"gender":2,"id":1327,"known_for_department":"Acting","name":"Ian McKellen","original_name":"Ian McKellen","popularity":21.445,"profile_path":"/5cnnnpnJG6TiYUSS7qgJheUZgnv.jpg","cast_id":20,"character":"Gandalf","credit_id":"52fe4a87c3a368484e158bb7","order":0},{"adult":false,"gender":2,"id":7060,"known_for_department":"Acting","name":"Martin Freeman","original_name":"Martin Freeman","popularity":23.056,"profile_path":"/pLG7mmxBXXTVAgzXvQl0ap3qlJU.jpg","cast_id":10,"character":"Bilbo Baggins","credit_id":"52fe4a87c3a368484e158b93","order":1},{"adult":false,"gender":2,"id":30315,"known_for_department":"Acting","name":"Richard Armitage","original_name":"Richard Armitage","popularity":22.802,"profile_path":"/lRWWodfrOd5SaLnFrz7UryFhasI.jpg","cast_id":17,"character":"Thorin Oakenshield","credit_id":"52fe4a87c3a368484e158bab","order":2},{"adult":false,"gender":2,"id":114,"known_for_department":"Acting","name":"Orlando Bloom","original_name":"Orlando Bloom","popularity":28.683,"profile_path":"/pulwUR0lZ8IWwXUCRXCnyWfYvNL.jpg","cast_id":14,"character":"Legolas","credit_id":"52fe4a87c3a368484e158b9f","order":3},{"adult":false,"gender":1,"id":19034,"known_for_department":"Acting","name":"Evangeline Lilly","original_name":"Evangeline Lilly","popularity":35.968,"profile_path":"/zgztLIWTJZm3vjGU7ezhF8GXESJ.jpg","cast_id":41,"character":"Tauriel","credit_id":"52fe4a88c3a368484e158c0b","order":4}],"directors":[{"adult":false,"gender":2,"id":108,"known_for_department":"Directing","name":"Peter Jackson","original_name":"Peter Jackson","popularity":19.935,"profile_path":"/4hh7hips4xc6kgpNDQKQH3goRvJ.jpg","credit_id":"52fe4a87c3a368484e158b65","department":"Directing","job":"Director"}],"keyPerson":{"adult":false,"gender":2,"id":7060,"known_for_department":"Acting","name":"Martin Freeman","original_name":"Martin Freeman","popularity":23.056,"profile_path":"/pLG7mmxBXXTVAgzXvQl0ap3qlJU.jpg","cast_id":10,"character":"Bilbo Baggins","credit_id":"52fe4a87c3a368484e158b93","order":1}},{"adult":false,"backdrop_path":"/xUWf5xX0AnZgAnYXAMk03zTbsef.jpg","genre_ids":[35,10749,18],"id":508,"original_language":"en","original_title":"Love Actually","overview":"'Love Actually' follows the lives of eight very different couples dealing with their love lives, in various loosely and interrelated tales, all set during a frantic month before Christmas in London, England.","popularity":16.705,"poster_path":"/7QPeVsr9rcFU9Gl90yg0gTOTpVv.jpg","release_date":"2003-11-07","title":"Love Actually","video":false,"vote_average":7.1,"vote_count":5607,"cast":[{"adult":false,"gender":2,"id":3291,"known_for_department":"Acting","name":"Hugh Grant","original_name":"Hugh Grant","popularity":15.682,"profile_path":"/piTC1mCFr6ZCS3SdaN5qF9Vnqu7.jpg","cast_id":30,"character":"The Prime Minister","credit_id":"52fe424bc3a36847f8013385","order":0},{"adult":false,"gender":2,"id":3896,"known_for_department":"Acting","name":"Liam Neeson","original_name":"Liam Neeson","popularity":66.917,"profile_path":"/bboldwqSC6tdw2iL6631c98l2Mn.jpg","cast_id":20,"character":"Daniel","credit_id":"52fe424bc3a36847f8013361","order":1},{"adult":false,"gender":2,"id":4566,"known_for_department":"Acting","name":"Alan Rickman","original_name":"Alan Rickman","popularity":9.351,"profile_path":"/7tADZs4ILE93oJ5pAh6mKQFEq2m.jpg","cast_id":33,"character":"Harry","credit_id":"52fe424bc3a36847f8013391","order":2},{"adult":false,"gender":1,"id":7056,"known_for_department":"Acting","name":"Emma Thompson","original_name":"Emma Thompson","popularity":27.847,"profile_path":"/xr8Ki3CIqweWWqS5q0kUYdiK6oQ.jpg","cast_id":21,"character":"Karen","credit_id":"52fe424bc3a36847f8013365","order":3},{"adult":false,"gender":2,"id":2440,"known_for_department":"Acting","name":"Bill Nighy","original_name":"Bill Nighy","popularity":35.699,"profile_path":"/acbigDOU1L1vMWAL3Wf0r8h8qLA.jpg","cast_id":15,"character":"Billy Mack","credit_id":"52fe424bc3a36847f8013351","order":4}],"directors":[{"adult":false,"gender":2,"id":7018,"known_for_department":"Writing","name":"Richard Curtis","original_name":"Richard Curtis","popularity":9.041,"profile_path":"/idJ1oulpoD7UAy9odVBcxUyAabW.jpg","credit_id":"52fe424bc3a36847f8013305","department":"Directing","job":"Director"}],"keyPerson":{"adult":false,"gender":2,"id":2440,"known_for_department":"Acting","name":"Bill Nighy","original_name":"Bill Nighy","popularity":35.699,"profile_path":"/acbigDOU1L1vMWAL3Wf0r8h8qLA.jpg","cast_id":15,"character":"Billy Mack","credit_id":"52fe424bc3a36847f8013351","order":4}}]}