{"puzzleId":1664427729066,"puzzle":[{"adult":false,"backdrop_path":"/l45UqyARB3WxpYNuACjMjndpe85.jpg","genre_ids":[16,10751,35,14,12],"id":809,"original_language":"en","original_title":"Shrek 2","overview":"Shrek, Fiona and Donkey set off to Far, Far Away to meet Fiona's mother and father. But not everyone is happy. Shrek and the King find it hard to get along, and there's tension in the marriage. The fairy godmother discovers that Shrek has married Fiona instead of her Son Prince Charming and sets about destroying their marriage.","popularity":171.762,"poster_path":"/2yYP0PQjG8zVqturh1BAqu2Tixl.jpg","release_date":"2004-05-19","title":"Shrek 2","video":false,"vote_average":7.2,"vote_count":10259,"cast":[{"adult":false,"gender":2,"id":12073,"known_for_department":"Acting","name":"Mike Myers","original_name":"Mike Myers","popularity":24.357,"profile_path":"/gjfDl52Kk02MPgUYFjs9bOy33OY.jpg","cast_id":29,"character":"Shrek (voice)","credit_id":"52fe4279c3a36847f80219ad","order":0},{"adult":false,"gender":2,"id":776,"known_for_department":"Acting","name":"Eddie Murphy","original_name":"Eddie Murphy","popularity":22.554,"profile_path":"/35NneLV2mx3c4eHptwcCMDmihik.jpg","cast_id":18,"character":"Donkey (voice)","credit_id":"52fe4279c3a36847f802197f","order":1},{"adult":false,"gender":1,"id":6941,"known_for_department":"Acting","name":"Cameron Diaz","original_name":"Cameron Diaz","popularity":20.409,"profile_path":"/tIWUyvmJayu8gtbrzCWC0L3H8kH.jpg","cast_id":19,"character":"Princess Fiona (voice)","credit_id":"52fe4279c3a36847f8021983","order":2},{"adult":false,"gender":1,"id":5823,"known_for_department":"Acting","name":"Julie Andrews","original_name":"Julie Andrews","popularity":11.146,"profile_path":"/kTXM2KfsXh2vSav0s9vaDKfs4lR.jpg","cast_id":20,"character":"Queen (voice)","credit_id":"52fe4279c3a36847f8021987","order":3},{"adult":false,"gender":2,"id":3131,"known_for_department":"Acting","name":"Antonio Banderas","original_name":"Antonio Banderas","popularity":30.809,"profile_path":"/iWIUEwgn2KW50MssR7tdPeFoRGW.jpg","cast_id":21,"character":"Puss in Boots (voice)","credit_id":"52fe4279c3a36847f802198b","order":4}],"directors":[{"adult":false,"gender":2,"id":5524,"known_for_department":"Production","name":"Andrew Adamson","original_name":"Andrew Adamson","popularity":7.785,"profile_path":"/qqIAVKAe5LHRbPyZUlptsqlo4Kb.jpg","credit_id":"52fe4279c3a36847f802191b","department":"Directing","job":"Director"},{"adult":false,"gender":2,"id":12079,"known_for_department":"Directing","name":"Kelly Asbury","original_name":"Kelly Asbury","popularity":7.006,"profile_path":"/fzHQFYLc1zVVn3dUjr6pMuKdE0U.jpg","credit_id":"52fe4279c3a36847f8021921","department":"Directing","job":"Director"},{"adult":false,"gender":2,"id":12080,"known_for_department":"Acting","name":"Conrad Vernon","original_name":"Conrad Vernon","popularity":8.551,"profile_path":"/c7MIz3sy6UPhBh9YnThd7j8ypdl.jpg","credit_id":"52fe4279c3a36847f8021927","department":"Directing","job":"Director"}],"keyPerson":{"adult":false,"gender":1,"id":6941,"known_for_department":"Acting","name":"Cameron Diaz","original_name":"Cameron Diaz","popularity":20.409,"profile_path":"/tIWUyvmJayu8gtbrzCWC0L3H8kH.jpg","cast_id":19,"character":"Princess Fiona (voice)","credit_id":"52fe4279c3a36847f8021983","order":2}},{"adult":false,"backdrop_path":"/r1gLQFbpkWWLrOEPmpqzzMIUxxj.jpg","genre_ids":[28,53,878,9648],"id":180,"original_language":"en","original_title":"Minority Report","overview":"John Anderton is a top 'Precrime' cop in the late-21st century, when technology can predict crimes before they're committed. But Anderton becomes the quarry when another investigator targets him for a murder charge.","popularity":27.425,"poster_path":"/ccqpHq5tk5W4ymbSbuoy4uYOxFI.jpg","release_date":"2002-06-21","title":"Minority Report","video":false,"vote_average":7.3,"vote_count":7329,"cast":[{"adult":false,"gender":2,"id":500,"known_for_department":"Acting","name":"Tom Cruise","original_name":"Tom Cruise","popularity":70.706,"profile_path":"/8qBylBsQf4llkGrWR3qAsOtOU8O.jpg","cast_id":5,"character":"Chief John Anderton","credit_id":"52fe4223c3a36847f8006f53","order":0},{"adult":false,"gender":2,"id":72466,"known_for_department":"Acting","name":"Colin Farrell","original_name":"Colin Farrell","popularity":45.571,"profile_path":"/3iHqlaeSAQwJ0KraRKD1A4vBaCS.jpg","cast_id":11,"character":"Danny Witwer","credit_id":"52fe4223c3a36847f8006f67","order":1},{"adult":false,"gender":1,"id":2206,"known_for_department":"Acting","name":"Samantha Morton","original_name":"Samantha Morton","popularity":21.445,"profile_path":"/5DOlLIlgxKYzb4Hsm0phrGmYVIq.jpg","cast_id":12,"character":"Agatha","credit_id":"52fe4223c3a36847f8006f6b","order":2},{"adult":false,"gender":2,"id":2201,"known_for_department":"Acting","name":"Max von Sydow","original_name":"Max von Sydow","popularity":22.373,"profile_path":"/aUFBsGCN6qpcjsF14LccMzE5ye7.jpg","cast_id":6,"character":"Director Lamar Burgess","credit_id":"52fe4223c3a36847f8006f57","order":3},{"adult":false,"gender":2,"id":53,"known_for_department":"Acting","name":"Peter Stormare","original_name":"Peter Stormare","popularity":31.899,"profile_path":"/5muzSVt66Qxc8KuVbq0phZIN9tj.jpg","cast_id":15,"character":"Dr. Solomon Eddie","credit_id":"52fe4223c3a36847f8006f77","order":4}],"directors":[{"adult":false,"gender":2,"id":488,"known_for_department":"Directing","name":"Steven Spielberg","original_name":"Steven Spielberg","popularity":30.956,"profile_path":"/tZxcg19YQ3e8fJ0pOs7hjlnmmr6.jpg","credit_id":"52fe4223c3a36847f8006f3d","department":"Directing","job":"Director"}],"keyPerson":{"adult":false,"gender":2,"id":500,"known_for_department":"Acting","name":"Tom Cruise","original_name":"Tom Cruise","popularity":70.706,"profile_path":"/8qBylBsQf4llkGrWR3qAsOtOU8O.jpg","cast_id":5,"character":"Chief John Anderton","credit_id":"52fe4223c3a36847f8006f53","order":0}},{"adult":false,"backdrop_path":"/odJ4hx6g6vBt4lBWKFD1tI8WS4x.jpg","genre_ids":[28,18],"id":361743,"original_language":"en","original_title":"Top Gun: Maverick","overview":"After more than thirty years of service as one of the Navy’s top aviators, and dodging the advancement in rank that would ground him, Pete “Maverick” Mitchell finds himself training a detachment of TOP GUN graduates for a specialized mission the likes of which no living pilot has ever seen.","popularity":1177.19,"poster_path":"/62HCnUTziyWcpDaBO2i1DX17ljH.jpg","release_date":"2022-05-27","title":"Top Gun: Maverick","video":false,"vote_average":8.4,"vote_count":4008,"cast":[{"adult":false,"gender":2,"id":996701,"known_for_department":"Acting","name":"Miles Teller","original_name":"Miles Teller","popularity":69.268,"profile_path":"/cg3LW0xX6RKr8dmescxq1bepcb5.jpg","cast_id":12,"character":"Lt. Bradley 'Rooster' Bradshaw","credit_id":"5b3bf2b992514102e2002a1d","order":1},{"adult":false,"gender":1,"id":6161,"known_for_department":"Acting","name":"Jennifer Connelly","original_name":"Jennifer Connelly","popularity":192.098,"profile_path":"/egh1eOHuYgeoqdlLQgaXMl6cPOm.jpg","cast_id":13,"character":"Penny Benjamin","credit_id":"5b524c4e9251411f84000faa","order":2},{"adult":false,"gender":2,"id":65717,"known_for_department":"Acting","name":"Jon Hamm","original_name":"Jon Hamm","popularity":29.829,"profile_path":"/mrXE5fZbEDPc7BEE5G21J6qrwzi.jpg","cast_id":41,"character":"Adm. Beau 'Cyclone' Simpson","credit_id":"5d8481cd1f748b023c89e2e8","order":3},{"adult":false,"gender":2,"id":83271,"known_for_department":"Acting","name":"Glen Powell","original_name":"Glen Powell","popularity":46.54,"profile_path":"/o1UZnQasM49w7OIUiE9YEdS0wqg.jpg","cast_id":15,"character":"Lt. Jake 'Hangman' Seresin","credit_id":"5b799ae10e0a264728031805","order":4},{"adult":false,"gender":2,"id":228,"known_for_department":"Acting","name":"Ed Harris","original_name":"Ed Harris","popularity":39.611,"profile_path":"/ryF0KkljweLhPkQ70x6w3u9Qjjj.jpg","cast_id":40,"character":"Radm. Chester 'Hammer' Cain","credit_id":"5d311eebcaab6d0b29a0f4cc","order":5}],"directors":[{"adult":false,"gender":2,"id":86270,"known_for_department":"Directing","name":"Joseph Kosinski","original_name":"Joseph Kosinski","popularity":11.702,"profile_path":"/oWLUXWY0j8TYzwnf2wETYWO181S.jpg","credit_id":"5925e0fac3a36877fd011ca8","department":"Directing","job":"Director"}],"keyPerson":{"adult":false,"gender":2,"id":996701,"known_for_department":"Acting","name":"Miles Teller","original_name":"Miles Teller","popularity":69.268,"profile_path":"/cg3LW0xX6RKr8dmescxq1bepcb5.jpg","cast_id":12,"character":"Lt. Bradley 'Rooster' Bradshaw","credit_id":"5b3bf2b992514102e2002a1d","order":1}},{"adult":false,"backdrop_path":"/8YNNyQiPZlF9qv5EGOUK20mnXVk.jpg","genre_ids":[28,12,878,53],"id":262500,"original_language":"en","original_title":"Insurgent","overview":"Beatrice Prior must confront her inner demons and continue her fight against a powerful alliance which threatens to tear her society apart.","popularity":67.187,"poster_path":"/dP5Fb6YRfzmCQtRbHOr2kO7tJW9.jpg","release_date":"2015-03-20","title":"Insurgent","video":false,"vote_average":6.4,"vote_count":9042,"cast":[{"adult":false,"gender":1,"id":94185,"known_for_department":"Acting","name":"Shailene Woodley","original_name":"Shailene Woodley","popularity":25.441,"profile_path":"/gL2NvHKW9wAH3qkZuJ76ULUiArB.jpg","cast_id":0,"character":"Beatrice \"Tris\" Prior","credit_id":"533a707a9251417d9b005bc5","order":0},{"adult":false,"gender":2,"id":587020,"known_for_department":"Acting","name":"Theo James","original_name":"Theo James","popularity":46.251,"profile_path":"/ejUHDsEsERj2kEujoB4QEqG8Shr.jpg","cast_id":1,"character":"Tobias \"Four\" Eaton","credit_id":"533a70d0c3a3680e69007788","order":1},{"adult":false,"gender":1,"id":6944,"known_for_department":"Acting","name":"Octavia Spencer","original_name":"Octavia Spencer","popularity":13.454,"profile_path":"/zDGydyM1fmvNWzQlTAns9IZjNxT.jpg","cast_id":19,"character":"Johanna Reyes","credit_id":"5431e22d0e0a2658b2002ca0","order":2},{"adult":false,"gender":2,"id":224181,"known_for_department":"Acting","name":"Jai Courtney","original_name":"Jai Courtney","popularity":24.937,"profile_path":"/9kMUy38pj7oTCuQUhfkbgXOedCq.jpg","cast_id":14,"character":"Eric Coulter","credit_id":"5431e1efc3a36811ef002cf0","order":3},{"adult":false,"gender":2,"id":56614,"known_for_department":"Acting","name":"Ray Stevenson","original_name":"Ray Stevenson","popularity":19.37,"profile_path":"/msafbswGI6uisRuNvQ8a1wMF5Ca.jpg","cast_id":18,"character":"Marcus Eaton","credit_id":"5431e2230e0a2658b2002c9d","order":4}],"directors":[{"adult":false,"gender":2,"id":57270,"known_for_department":"Directing","name":"Robert Schwentke","original_name":"Robert Schwentke","popularity":4.596,"profile_path":"/awPMXTPvBQFlUWVt8I7WOv8ajYg.jpg","credit_id":"533a71a6c3a3680e7000765e","department":"Directing","job":"Director"}],"keyPerson":{"adult":false,"gender":1,"id":6944,"known_for_department":"Acting","name":"Octavia Spencer","original_name":"Octavia Spencer","popularity":13.454,"profile_path":"/zDGydyM1fmvNWzQlTAns9IZjNxT.jpg","cast_id":19,"character":"Johanna Reyes","credit_id":"5431e22d0e0a2658b2002ca0","order":2}},{"adult":false,"backdrop_path":"/wyvUmyzqGOBDyqLHRSukGDjI7bH.jpg","genre_ids":[18],"id":50014,"original_language":"en","original_title":"The Help","overview":"Aibileen Clark is a middle-aged African-American maid who has spent her life raising white children and has recently lost her only son; Minny Jackson is an African-American maid who has often offended her employers despite her family's struggles with money and her desperate need for jobs; and Eugenia \"Skeeter\" Phelan is a young white woman who has recently moved back home after graduating college to find out her childhood maid has mysteriously disappeared. These three stories intertwine to explain how life in Jackson, Mississippi revolves around \"the help\"; yet they are always kept at a certain distance because of racial lines.","popularity":99.878,"poster_path":"/7XLSwxpfpPoJyTdJVot6a42TS2V.jpg","release_date":"2011-08-10","title":"The Help","video":false,"vote_average":8.2,"vote_count":6701,"cast":[{"adult":false,"gender":1,"id":54693,"known_for_department":"Acting","name":"Emma Stone","original_name":"Emma Stone","popularity":28.075,"profile_path":"/cZ8a3QvAnj2cgcgVL6g4XaqPzpL.jpg","cast_id":10,"character":"Eugenia \"Skeeter\" Phelan","credit_id":"52fe47b5c3a36847f814403f","order":0},{"adult":false,"gender":1,"id":19492,"known_for_department":"Acting","name":"Viola Davis","original_name":"Viola Davis","popularity":21.427,"profile_path":"/xDssw6vpYNRjsybvMPRE30e0dPN.jpg","cast_id":6,"character":"Aibileen Clark","credit_id":"52fe47b5c3a36847f814402f","order":1},{"adult":false,"gender":1,"id":18997,"known_for_department":"Acting","name":"Bryce Dallas Howard","original_name":"Bryce Dallas Howard","popularity":41.87,"profile_path":"/qQX1rhQaJ1G8eMG2RknFKiXfNRc.jpg","cast_id":11,"character":"Hilly Holbrook","credit_id":"52fe47b5c3a36847f8144043","order":3},{"adult":false,"gender":1,"id":83002,"known_for_department":"Acting","name":"Jessica Chastain","original_name":"Jessica Chastain","popularity":30.638,"profile_path":"/mR1ELpP0T2Q1ZRSaADPgtrbPGla.jpg","cast_id":14,"character":"Celia Foote","credit_id":"52fe47b5c3a36847f814404f","order":4},{"adult":false,"gender":1,"id":221098,"known_for_department":"Acting","name":"Anna Camp","original_name":"Anna Camp","popularity":25.209,"profile_path":"/yOGBODtjYsZnQH8p7dZb0S015Pf.jpg","cast_id":21,"character":"Jolene French","credit_id":"52fe47b5c3a36847f8144077","order":5}],"directors":[{"adult":false,"gender":2,"id":55789,"known_for_department":"Directing","name":"Tate Taylor","original_name":"Tate Taylor","popularity":3.493,"profile_path":"/zJaLbNHLoQMhCAeJhn1J1B0xrup.jpg","credit_id":"52fe47b5c3a36847f814402b","department":"Directing","job":"Director"}],"keyPerson":{"adult":false,"gender":1,"id":221098,"known_for_department":"Acting","name":"Anna Camp","original_name":"Anna Camp","popularity":25.209,"profile_path":"/yOGBODtjYsZnQH8p7dZb0S015Pf.jpg","cast_id":21,"character":"Jolene French","credit_id":"52fe47b5c3a36847f8144077","order":5}},{"adult":false,"backdrop_path":"/p0pqnu9URsFzYwo55QbS3bfAamU.jpg","genre_ids":[35,18,10749],"id":339397,"original_language":"en","original_title":"Café Society","overview":"The story of a young man who arrives in Hollywood during the 1930s hoping to work in the film industry, falls in love, and finds himself swept up in the vibrant café society that defined the spirit of the age.","popularity":15.32,"poster_path":"/q9fohCRpQ7m8OTyi82fxa3B86te.jpg","release_date":"2016-07-15","title":"Café Society","video":false,"vote_average":6.5,"vote_count":2427,"cast":[{"adult":false,"gender":2,"id":44735,"known_for_department":"Acting","name":"Jesse Eisenberg","original_name":"Jesse Eisenberg","popularity":35.497,"profile_path":"/yYhwWRcxDHTn63gSEF1vnDAD7cD.jpg","cast_id":2,"character":"Bobby Dorfman","credit_id":"554d483ec3a3685e4c005f7a","order":0},{"adult":false,"gender":1,"id":37917,"known_for_department":"Acting","name":"Kristen Stewart","original_name":"Kristen Stewart","popularity":32.955,"profile_path":"/pLYLmzWHzLAUESBp9p4edXXQCVO.jpg","cast_id":1,"character":"Vonnie Sybil","credit_id":"554d4839c3a36824cd002a19","order":1},{"adult":false,"gender":2,"id":4495,"known_for_department":"Acting","name":"Steve Carell","original_name":"Steve Carell","popularity":41.17,"profile_path":"/dzJtsLspH5Bf8Tvw7OQC47ETNfJ.jpg","cast_id":11,"character":"Phil Stern","credit_id":"55e27e5ec3a3680b6c001746","order":2},{"adult":false,"gender":1,"id":59175,"known_for_department":"Acting","name":"Blake Lively","original_name":"Blake Lively","popularity":21.033,"profile_path":"/rkGVjd6wImtgjOCi0IpeffdEWtb.jpg","cast_id":0,"character":"Veronica Hayes","credit_id":"554d48329251413fcf002946","order":3},{"adult":false,"gender":1,"id":7489,"known_for_department":"Acting","name":"Parker Posey","original_name":"Parker Posey","popularity":14.844,"profile_path":"/1YXYlqhp8cTO5LP8sBuWVIVmsOE.jpg","cast_id":12,"character":"Rad Taylor","credit_id":"55f63ccb9251413ed900185b","order":4}],"directors":[{"adult":false,"gender":2,"id":1243,"known_for_department":"Directing","name":"Woody Allen","original_name":"Woody Allen","popularity":10.676,"profile_path":"/wcPQgZLDibuej1RwNTy1R2U2ZJw.jpg","credit_id":"554d486292514140c3002972","department":"Directing","job":"Director"}],"keyPerson":{"adult":false,"gender":1,"id":59175,"known_for_department":"Acting","name":"Blake Lively","original_name":"Blake Lively","popularity":21.033,"profile_path":"/rkGVjd6wImtgjOCi0IpeffdEWtb.jpg","cast_id":0,"character":"Veronica Hayes","credit_id":"554d48329251413fcf002946","order":3}}]}