{"puzzleId":1665556546018,"puzzle":[{"adult":false,"backdrop_path":"/jzdnhRhG0dsuYorwvSqPqqnM1cV.jpg","genre_ids":[28,80,53],"id":337339,"original_language":"en","original_title":"The Fate of the Furious","overview":"When a mysterious woman seduces Dom into the world of crime and a betrayal of those closest to him, the crew face trials that will test them as never before.","popularity":102.935,"poster_path":"/dImWM7GJqryWJO9LHa3XQ8DD5NH.jpg","release_date":"2017-04-14","title":"The Fate of the Furious","video":false,"vote_average":6.9,"vote_count":9100,"cast":[{"adult":false,"gender":2,"id":12835,"known_for_department":"Acting","name":"Vin Diesel","original_name":"Vin Diesel","popularity":72.64,"profile_path":"/7rwSXluNWZAluYMOEWBxkPmckES.jpg","cast_id":390,"character":"Dominic Toretto","credit_id":"5ceab3dc9251414398b96e7a","order":0},{"adult":false,"gender":2,"id":976,"known_for_department":"Acting","name":"Jason Statham","original_name":"Jason Statham","popularity":115.139,"profile_path":"/whNwkEQYWLFJA8ij0WyOOAD5xhQ.jpg","cast_id":12,"character":"Deckard Shaw","credit_id":"5595cbda9251414e06000173","order":1},{"adult":false,"gender":2,"id":18918,"known_for_department":"Acting","name":"Dwayne Johnson","original_name":"Dwayne Johnson","popularity":63.445,"profile_path":"/cgoy7t5Ve075naBPcewZrc08qGw.jpg","cast_id":1,"character":"Luke Hobbs","credit_id":"553bb63fc3a368746200017c","order":2},{"adult":false,"gender":1,"id":17647,"known_for_department":"Acting","name":"Michelle Rodriguez","original_name":"Michelle Rodriguez","popularity":15.9,"profile_path":"/xSvkVrLz6xas1mCeOR9i4QtmhnQ.jpg","cast_id":25,"character":"Letty Ortiz","credit_id":"57a2a7a4c3a36832b80025c6","order":3},{"adult":false,"gender":2,"id":8169,"known_for_department":"Acting","name":"Tyrese Gibson","original_name":"Tyrese Gibson","popularity":16.682,"profile_path":"/eHhIFk7HOElgFCaD4igtAgn41kA.jpg","cast_id":27,"character":"Roman Pearce","credit_id":"57a2a7b7c3a36833a6002589","order":4}],"directors":[{"adult":false,"gender":2,"id":37932,"known_for_department":"Directing","name":"F. Gary Gray","original_name":"F. Gary Gray","popularity":3.05,"profile_path":"/gAM7rzBe0i9LMG7rX24y3ekPW5x.jpg","credit_id":"56b41f91c3a36806f100355a","department":"Directing","job":"Director"}],"keyPerson":{"adult":false,"gender":1,"id":17647,"known_for_department":"Acting","name":"Michelle Rodriguez","original_name":"Michelle Rodriguez","popularity":15.9,"profile_path":"/xSvkVrLz6xas1mCeOR9i4QtmhnQ.jpg","cast_id":25,"character":"Letty Ortiz","credit_id":"57a2a7a4c3a36832b80025c6","order":3}},{"adult":false,"backdrop_path":"/cHkhb5A4gQRK6zs6Pv7zorHs8Nk.jpg","genre_ids":[28,53,80,12],"id":168259,"original_language":"en","original_title":"Furious 7","overview":"Deckard Shaw seeks revenge against Dominic Toretto and his family for his comatose brother.","popularity":107.094,"poster_path":"/ktofZ9Htrjiy0P6LEowsDaxd3Ri.jpg","release_date":"2015-04-03","title":"Furious 7","video":false,"vote_average":7.2,"vote_count":9329,"cast":[{"adult":false,"gender":2,"id":8167,"known_for_department":"Acting","name":"Paul Walker","original_name":"Paul Walker","popularity":16.017,"profile_path":"/7YTW0WOeu2slssEtPTSzrLiPmXu.jpg","cast_id":19,"character":"Brian O'Conner","credit_id":"5431dfe4c3a3681143002b98","order":1},{"adult":false,"gender":2,"id":8171,"known_for_department":"Acting","name":"Ludacris","original_name":"Ludacris","popularity":16.051,"profile_path":"/erkJijujhe48vhJ8iCEtVpNEeVn.jpg","cast_id":31,"character":"Tej Parker","credit_id":"5431e0520e0a2658b2002c3c","order":5},{"adult":false,"gender":1,"id":22123,"known_for_department":"Acting","name":"Jordana Brewster","original_name":"Jordana Brewster","popularity":15.327,"profile_path":"/8VzFsSfT7NnMGyH5JQBQdTxDHcO.jpg","cast_id":24,"character":"Mia Toretto","credit_id":"5431e00dc3a36811ef002c7e","order":6},{"adult":false,"gender":2,"id":938,"known_for_department":"Acting","name":"Djimon Hounsou","original_name":"Djimon Hounsou","popularity":23.898,"profile_path":"/hco0KMbrxACYTmBfAkSzCf23CXV.jpg","cast_id":25,"character":"Jakande","credit_id":"5431e015c3a36831a90040da","order":7},{"adult":false,"gender":2,"id":57207,"known_for_department":"Acting","name":"Tony Jaa","original_name":"Tony Jaa","popularity":17.299,"profile_path":"/AdN11kgJeKgjyWPRTGSHjSPzG7N.jpg","cast_id":30,"character":"Kiet","credit_id":"5431e04a0e0a26464300432c","order":8}],"directors":[{"adult":false,"gender":2,"id":2127,"known_for_department":"Production","name":"James Wan","original_name":"James Wan","popularity":17.343,"profile_path":"/bNJccMIKzCtYnndcOKniSKCzo5Y.jpg","credit_id":"52fe4cc8c3a36847f823e699","department":"Directing","job":"Director"}],"keyPerson":{"adult":false,"gender":2,"id":57207,"known_for_department":"Acting","name":"Tony Jaa","original_name":"Tony Jaa","popularity":17.299,"profile_path":"/AdN11kgJeKgjyWPRTGSHjSPzG7N.jpg","cast_id":30,"character":"Kiet","credit_id":"5431e04a0e0a26464300432c","order":8}},{"adult":false,"backdrop_path":"/jeAQdDX9nguP6YOX6QSWKDPkbBo.jpg","genre_ids":[28,878,14],"id":590706,"original_language":"en","original_title":"Jiu Jitsu","overview":"Every six years, an ancient order of jiu-jitsu fighters joins forces to battle a vicious race of alien invaders. But when a celebrated war hero goes down in defeat, the fate of the planet and mankind hangs in the balance.","popularity":78.741,"poster_path":"/eLT8Cu357VOwBVTitkmlDEg32Fs.jpg","release_date":"2020-11-20","title":"Jiu Jitsu","video":false,"vote_average":4.9,"vote_count":511,"cast":[{"adult":false,"gender":2,"id":2963,"known_for_department":"Acting","name":"Nicolas Cage","original_name":"Nicolas Cage","popularity":50.602,"profile_path":"/ar33qcWbEgREn07ZpXv5Pbj8hbM.jpg","cast_id":1,"character":"Wylie","credit_id":"5c991cdd9251417760f4a8c4","order":0},{"adult":false,"gender":2,"id":1427888,"known_for_department":"Acting","name":"Alain Moussi","original_name":"Alain Moussi","popularity":7.845,"profile_path":"/cIpMdm0ggxVmZIBVj7vz8Q8nPLT.jpg","cast_id":11,"character":"Jake","credit_id":"5d299594caab6d66599c5c23","order":1},{"adult":false,"gender":2,"id":81685,"known_for_department":"Acting","name":"Frank Grillo","original_name":"Frank Grillo","popularity":25.438,"profile_path":"/br2nPzelch2Tb3pZHnYAbXng7cz.jpg","cast_id":7,"character":"Harrigan","credit_id":"5d299566caab6d66599c5b4b","order":2},{"adult":false,"gender":1,"id":1296430,"known_for_department":"Acting","name":"JuJu Chan","original_name":"JuJu Chan","popularity":6.516,"profile_path":"/5JqRo0pJs1dWLS8vGfNPVJmF67u.jpg","cast_id":10,"character":"Carmen","credit_id":"5d29958ccaab6d0f719b3b33","order":4},{"adult":false,"gender":1,"id":140114,"known_for_department":"Acting","name":"Marie Avgeropoulos","original_name":"Marie Avgeropoulos","popularity":15.066,"profile_path":"/cCzCHmDZXrNfyzbkpxvaKDaGy77.jpg","cast_id":23,"character":"Myra","credit_id":"5f868315fcb8cc00357ffdd2","order":5}],"directors":[{"adult":false,"gender":2,"id":41355,"known_for_department":"Directing","name":"Dimitri Logothetis","original_name":"Dimitri Logothetis","popularity":3.676,"profile_path":"/c1sLBTi3hvPouSj6tRnHsjstRmU.jpg","credit_id":"5c991d070e0a264cc6c3c628","department":"Directing","job":"Director"}],"keyPerson":{"adult":false,"gender":2,"id":2963,"known_for_department":"Acting","name":"Nicolas Cage","original_name":"Nicolas Cage","popularity":50.602,"profile_path":"/ar33qcWbEgREn07ZpXv5Pbj8hbM.jpg","cast_id":1,"character":"Wylie","credit_id":"5c991cdd9251417760f4a8c4","order":0}},{"adult":false,"backdrop_path":"/9LuL3pwJiwIWSckeCbOX8G12F4X.jpg","genre_ids":[28,12,16,878],"id":324857,"original_language":"en","original_title":"Spider-Man: Into the Spider-Verse","overview":"Miles Morales is juggling his life between being a high school student and being a spider-man. When Wilson \"Kingpin\" Fisk uses a super collider, others from across the Spider-Verse are transported to this dimension.","popularity":111.381,"poster_path":"/iiZZdoQBEYBv6id8su7ImL0oCbD.jpg","release_date":"2018-12-14","title":"Spider-Man: Into the Spider-Verse","video":false,"vote_average":8.4,"vote_count":11829,"cast":[{"adult":false,"gender":2,"id":587506,"known_for_department":"Acting","name":"Shameik Moore","original_name":"Shameik Moore","popularity":6.469,"profile_path":"/gaSgfLOp9PiKVYmAEuLrcnwP7gV.jpg","cast_id":16,"character":"Miles Morales / Spider-Man (voice)","credit_id":"59125a1dc3a36864d404c94c","order":0},{"adult":false,"gender":2,"id":543505,"known_for_department":"Acting","name":"Jake Johnson","original_name":"Jake Johnson","popularity":16.486,"profile_path":"/3gASdJlbZYxTDYMaX6ALo4BDEjN.jpg","cast_id":28,"character":"Peter B. Parker / Spider-Man (voice)","credit_id":"5ae66a5b9251410cec003d8b","order":1},{"adult":false,"gender":1,"id":130640,"known_for_department":"Acting","name":"Hailee Steinfeld","original_name":"Hailee Steinfeld","popularity":36.591,"profile_path":"/q4UpZMEuvNCN5lL5L6xa3ICpheJ.jpg","cast_id":29,"character":"Gwen Stacy / Spider-Woman (voice)","credit_id":"5b1817d592514170c2001972","order":2},{"adult":false,"gender":2,"id":932967,"known_for_department":"Acting","name":"Mahershala Ali","original_name":"Mahershala Ali","popularity":19.281,"profile_path":"/9ZmSejm5lnUVY5IJ1iNx2QEjnHb.jpg","cast_id":18,"character":"Uncle Aaron / Prowler (voice)","credit_id":"5a2bda7d925141032913ed45","order":3},{"adult":false,"gender":2,"id":226366,"known_for_department":"Acting","name":"Brian Tyree Henry","original_name":"Brian Tyree Henry","popularity":22.809,"profile_path":"/cHayMfavRrIlfPHLUl6ARuuI1AT.jpg","cast_id":19,"character":"Jefferson Davis (voice)","credit_id":"5a2bdab1c3a3680b961381f9","order":4}],"directors":[{"adult":false,"gender":2,"id":59918,"known_for_department":"Writing","name":"Rodney Rothman","original_name":"Rodney Rothman","popularity":3.641,"profile_path":"/75yKuJr1wL8qesEDYL2IHK67BEx.jpg","credit_id":"5c005a6c9251417e55014b78","department":"Directing","job":"Director"},{"adult":false,"gender":2,"id":151007,"known_for_department":"Directing","name":"Peter Ramsey","original_name":"Peter Ramsey","popularity":2.589,"profile_path":"/9vCpMCgf5R0EQkWbylKTvtxzsB.jpg","credit_id":"5a2bdad2925141032c13b87e","department":"Directing","job":"Director"},{"adult":false,"gender":2,"id":936670,"known_for_department":"Directing","name":"Bob Persichetti","original_name":"Bob Persichetti","popularity":2.47,"profile_path":"/e8ezXe2id6TRTxDsL9lTpw4pM93.jpg","credit_id":"57f3dcefc3a3682f800001d9","department":"Directing","job":"Director"}],"keyPerson":{"adult":false,"gender":1,"id":130640,"known_for_department":"Acting","name":"Hailee Steinfeld","original_name":"Hailee Steinfeld","popularity":36.591,"profile_path":"/q4UpZMEuvNCN5lL5L6xa3ICpheJ.jpg","cast_id":29,"character":"Gwen Stacy / Spider-Woman (voice)","credit_id":"5b1817d592514170c2001972","order":2}},{"adult":false,"backdrop_path":"/rmasNrfemw9YODz0xhlEBWanNyX.jpg","genre_ids":[18,12,37],"id":44264,"original_language":"en","original_title":"True Grit","overview":"Following the murder of her father by a hired hand, a 14-year-old farm girl sets out to capture the killer. To aid her, she hires the toughest U.S. Marshal she can find—a man with 'true grit'—Reuben J. 'Rooster' Cogburn.","popularity":21.512,"poster_path":"/ptkuKjtIgYRrcX87YzyBjQGh8YU.jpg","release_date":"2010-12-22","title":"True Grit","video":false,"vote_average":7.3,"vote_count":4543,"cast":[{"adult":false,"gender":2,"id":1229,"known_for_department":"Acting","name":"Jeff Bridges","original_name":"Jeff Bridges","popularity":29.864,"profile_path":"/xms1RAY6q7Lzp7wNeRCB0kzhucn.jpg","cast_id":24,"character":"Reuben J. \"Rooster\" Cogburn","credit_id":"52fe4681c3a36847f8102c4b","order":0},{"adult":false,"gender":2,"id":1892,"known_for_department":"Acting","name":"Matt Damon","original_name":"Matt Damon","popularity":48.194,"profile_path":"/At3JgvaNeEN4Z4ESKlhhes85Xo3.jpg","cast_id":26,"character":"LaBoeuf","credit_id":"52fe4681c3a36847f8102c53","order":2},{"adult":false,"gender":2,"id":16851,"known_for_department":"Acting","name":"Josh Brolin","original_name":"Josh Brolin","popularity":26.624,"profile_path":"/2WGHZaU5FUUKOgRNp23fgOfKSzU.jpg","cast_id":27,"character":"Tom Chaney","credit_id":"52fe4681c3a36847f8102c57","order":3},{"adult":false,"gender":2,"id":12834,"known_for_department":"Acting","name":"Barry Pepper","original_name":"Barry Pepper","popularity":13.829,"profile_path":"/pmdNUqrpsoozh7QYqUgEgZQ69cA.jpg","cast_id":28,"character":"\"Lucky\" Ned Pepper","credit_id":"52fe4681c3a36847f8102c5b","order":4},{"adult":false,"gender":2,"id":93210,"known_for_department":"Acting","name":"Domhnall Gleeson","original_name":"Domhnall Gleeson","popularity":30.815,"profile_path":"/uDbwncuKlqL0fAuucXSvgakJDrc.jpg","cast_id":32,"character":"Moon (The Kid)","credit_id":"52fe4681c3a36847f8102c6b","order":5}],"directors":[{"adult":false,"gender":2,"id":1223,"known_for_department":"Writing","name":"Joel Coen","original_name":"Joel Coen","popularity":8.021,"profile_path":"/rgVaJNkZCgMarUcZuUAsVfXMWk3.jpg","credit_id":"52fe4681c3a36847f8102c35","department":"Directing","job":"Director"},{"adult":false,"gender":2,"id":1224,"known_for_department":"Directing","name":"Ethan Coen","original_name":"Ethan Coen","popularity":4.094,"profile_path":"/ccvoiEe3gEMAth1Oy8SJxVeMcAk.jpg","credit_id":"52fe4681c3a36847f8102c2f","department":"Directing","job":"Director"}],"keyPerson":{"adult":false,"gender":2,"id":1892,"known_for_department":"Acting","name":"Matt Damon","original_name":"Matt Damon","popularity":48.194,"profile_path":"/At3JgvaNeEN4Z4ESKlhhes85Xo3.jpg","cast_id":26,"character":"LaBoeuf","credit_id":"52fe4681c3a36847f8102c53","order":2}},{"adult":false,"backdrop_path":"/3dPhs7hUnQLphDFzdkD407VZDYo.jpg","genre_ids":[18,12,878],"id":286217,"original_language":"en","original_title":"The Martian","overview":"During a manned mission to Mars, Astronaut Mark Watney is presumed dead after a fierce storm and left behind by his crew. But Watney has survived and finds himself stranded and alone on the hostile planet. With only meager supplies, he must draw upon his ingenuity, wit and spirit to subsist and find a way to signal to Earth that he is alive.","popularity":58.779,"poster_path":"/5BHuvQ6p9kfc091Z8RiFNhCwL4b.jpg","release_date":"2015-10-02","title":"The Martian","video":false,"vote_average":7.7,"vote_count":17432,"cast":[{"adult":false,"gender":1,"id":83002,"known_for_department":"Acting","name":"Jessica Chastain","original_name":"Jessica Chastain","popularity":25.648,"profile_path":"/mR1ELpP0T2Q1ZRSaADPgtrbPGla.jpg","cast_id":9,"character":"Melissa Lewis","credit_id":"5466c78eeaeb8172820008e4","order":1},{"adult":false,"gender":2,"id":8447,"known_for_department":"Acting","name":"Jeff Daniels","original_name":"Jeff Daniels","popularity":18.504,"profile_path":"/r0mkZJZnTSJO3HJRsMW5HtszxE8.jpg","cast_id":13,"character":"Teddy Sanders","credit_id":"54a7fe92c3a3680c33001972","order":2},{"adult":false,"gender":2,"id":48,"known_for_department":"Acting","name":"Sean Bean","original_name":"Sean Bean","popularity":32.812,"profile_path":"/kTjiABk3TJ3yI0Cto5RsvyT6V3o.jpg","cast_id":14,"character":"Mitch Henderson","credit_id":"54a7feb3c3a3680c33001977","order":3},{"adult":false,"gender":2,"id":5294,"known_for_department":"Acting","name":"Chiwetel Ejiofor","original_name":"Chiwetel Ejiofor","popularity":28.157,"profile_path":"/yguRiLswH6CFIx8T56i04dqxfO4.jpg","cast_id":18,"character":"Vincent Kapoor","credit_id":"54bad6fec3a3686c61006835","order":4},{"adult":false,"gender":2,"id":119589,"known_for_department":"Acting","name":"Donald Glover","original_name":"Donald Glover","popularity":8.741,"profile_path":"/nilV7NtnML6PDa9VrvxD79F85K9.jpg","cast_id":15,"character":"Rich Purnell","credit_id":"54bad6b792514136350018fe","order":5}],"directors":[{"adult":false,"gender":2,"id":578,"known_for_department":"Directing","name":"Ridley Scott","original_name":"Ridley Scott","popularity":11.563,"profile_path":"/zABJmN9opmqD4orWl3KSdCaSo7Q.jpg","credit_id":"53e88b1ac3a368399f0035c5","department":"Directing","job":"Director"}],"keyPerson":{"adult":false,"gender":1,"id":83002,"known_for_department":"Acting","name":"Jessica Chastain","original_name":"Jessica Chastain","popularity":25.648,"profile_path":"/mR1ELpP0T2Q1ZRSaADPgtrbPGla.jpg","cast_id":9,"character":"Melissa Lewis","credit_id":"5466c78eeaeb8172820008e4","order":1}}]}